im_export/__init__.py
im_export/admin.py
im_export/apps.py
im_export/resources.py
im_export/services.py
im_export/urls.py
im_export/views.py
im_export/tests/__init__.py
im_export/tests/import_example.csv
im_export/tests/import_example.json
im_export/tests/test_insuree.py
im_export/tests/test_rest.py
openimis_be_im_export-1.5.0.dist-info/licenses/LICENSE
openimis_be_im_export-1.5.0.dist-info/METADATA
openimis_be_im_export-1.5.0.dist-info/WHEEL
openimis_be_im_export-1.5.0.dist-info/top_level.txt
openimis_be_im_export-1.5.0.dist-info/RECORD
