Metadata-Version: 2.4
Name: openimis-be-im_export
Version: 1.5.0
Summary: The openIMIS Backend import-export reference module based on django-import-export.
Home-page: https://openimis.org/
Author: Patrick Delcroix
Author-email: patrick.delcroix@swisstph.ch
License: GNU AGPL v3
Classifier: Environment :: Web Environment
Classifier: Framework :: Django
Classifier: Framework :: Django :: 3.0
Classifier: Intended Audience :: Developers
Classifier: License :: OSI Approved :: GNU Affero General Public License v3
Classifier: Operating System :: OS Independent
Classifier: Programming Language :: Python
Classifier: Programming Language :: Python :: 3.9
License-File: LICENSE
Requires-Dist: django
Requires-Dist: django-import-export
Requires-Dist: tablib
Requires-Dist: django-import-export[xlsx]
Requires-Dist: tablib[xls]
Requires-Dist: xlrd
Requires-Dist: xlwt
Dynamic: author
Dynamic: author-email
Dynamic: classifier
Dynamic: home-page
Dynamic: license
Dynamic: license-file
Dynamic: requires-dist
Dynamic: summary
